buildbot_macports_custom_views/VERSION
buildbot_macports_custom_views/__init__.py
buildbot_macports_custom_views/static/scripts.js
buildbot_macports_custom_views/static/scripts.js.map
buildbot_macports_custom_views/static/styles.css
buildbot_macports_custom_views/static/styles.css.map
buildbot_macports_custom_views/static/styles.js
buildbot_macports_custom_views/static/styles.js.map
buildbot_macports_custom_views-0.1.2.dist-info/METADATA
buildbot_macports_custom_views-0.1.2.dist-info/WHEEL
buildbot_macports_custom_views-0.1.2.dist-info/entry_points.txt
buildbot_macports_custom_views-0.1.2.dist-info/top_level.txt
buildbot_macports_custom_views-0.1.2.dist-info/RECORD
